crosslinked/__init__.py
crosslinked/logger.py
crosslinked/search.py
crosslinked/utils.py
crosslinked-0.3.0.dist-info/LICENSE
crosslinked-0.3.0.dist-info/METADATA
crosslinked-0.3.0.dist-info/WHEEL
crosslinked-0.3.0.dist-info/entry_points.txt
crosslinked-0.3.0.dist-info/top_level.txt
crosslinked-0.3.0.dist-info/RECORD
