Metadata-Version: 2.1
Name: crosslinked
Version: 0.3.0
Home-page: https://github.com/m8sec/CrossLinked
Author: m8sec
License: GPLv3
Classifier: Environment :: Console
Classifier: Programming Language :: Python :: 3
Classifier: License :: OSI Approved :: GNU General Public License v3 or later (GPLv3+)
Classifier: Topic :: Security
License-File: LICENSE
Requires-Dist: bs4
Requires-Dist: lxml
Requires-Dist: requests
Requires-Dist: Unidecode
